{
	"results":[
		{
			"organization":"Aero Med",
			"structure":[
				{
					"title":"General Patient Care Information",
					"type":"folder",
					"contains":[
					
					]
				},
				{
					"title":"Logistics",
					"level":"1",
					"type":"folder",
					"contains":[
			
					]
				},
				{
					"title":"Medical Diagnoses",
					"type":"folder",
					"contains":[
						{
							"title":"Acute Alcohol Withdrawal",
							"type":"document",
							"contains":[
									
							]
						},
						{
							"title":"Acute Coronary Syndrome",
							"type":"document",
							"contains":[
									
							]
						},
						{
							"title":"Anaphylaxis",
							"type":"document",
							"contains":[
									
							]
						},
						{
							"title":"Aortic Aneurysm and Dissection",
							"type":"document",
							"contains":[
									
							]
						},
						{
							"title":"Arrhythmias, Unstable",
							"type":"document",
							"contains":[
									
							]
						},
						{
							"title":"Arterial Occlusion",
							"type":"document",
							"contains":[
									
							]
						},
						{
							"title":"Asthma and COPD",
							"type":"document",
							"contains":[
									
							]
						},
						{
							"title":"Carbon Monoxide Poisoning",
							"type":"document",
							"contains":[
									
							]
						},
						{
							"title":"Cardiac Arrest",
							"type":"document",
							"contains":[
									
							]
						},
						{
							"title":"Congestive Heart Failure and Pulmonary Edema",
							"type":"document",
							"contains":[
									
							]
						},
						{
							"title":"Disseminated Intravascular Coagulation",
							"type":"document",
							"contains":[
									
							]
						},
						{
							"title":"Electrolyte Imbalance and Renal Failure",
							"type":"document",
							"contains":[
									
							]
						},
						{
							"title":"Epiglottitis",
							"type":"document",
							"contains":[
									
							]
						},
						{
							"title":"GI Bleed",
							"type":"document",
							"contains":[
									
							]
						},
						{
							"title":"Hyperglycemia and Diabetic Ketoacidosis and Hyperosmolar Nonketotic Coma",
							"type":"document",
							"contains":[
									
							]
						},
						{
							"title":"Hypertensive Crisis",
							"type":"document",
							"contains":[
									
							]
						},
						{
							"title":"LVAD Transport Considerations",
							"type":"document",
							"contains":[
									
							]
						},
						{
							"title":"Meningitis",
							"type":"document",
							"contains":[
									
							]
						},
						{
							"title":"Necrotizing Fasciitis",
							"type":"document",
							"contains":[
									
							]
						},
						{
							"title":"Pulmonary Embolus",
							"type":"document",
							"contains":[
									
							]
						},
						{
							"title":"Respiratory Failure",
							"type":"document",
							"contains":[
									
							]
						},
						{
							"title":"Sepsis",
							"type":"document",
							"contains":[
									
							]
						},
						{
							"title":"Sickle Cell Crisis",
							"type":"document",
							"contains":[
									
							]
						},
						{
							"title":"Status Epilepticus and Seizures",
							"type":"document",
							"contains":[
									
							]
						},
						{
							"title":"Stroke Hermorrhagic",
							"type":"document",
							"contains":[
									
							]
						},
						{
							"title":"Stroke Ischemic",
							"type":"document",
							"contains":[
									
							]
						},
						{
							"title":"Thrombocytopenia and Heparin Induced Thrombocytopenia",
							"type":"document",
							"contains":[
									
							]
						},
						{
							"title":"Toxic Ingestion and Exposure",
							"type":"document",
							"contains":[
									
							]
						},
						{
							"title":"Violent or Combative Patient",
							"type":"document",
							"contains":[
									
							]
						}
					]
				},
				{
					"title":"Medications",
					"type":"folder",
					"contains":[
						{
							"title":"Adenocard-adenosine",
							"type":"document",
							"contains":[
									
							]
						},
						{
							"title":"Adrenalin-epinephrine",
							"type":"document",
							"contains":[
									
							]
						},
						{
							"title":"Amidate-etomidate",
							"type":"document",
							"contains":[
									
							]
						},
						{
							"title":"Anectine-succinlycholine",
							"type":"document",
							"contains":[
									
							]
						},
						{
							"title":"Apresoline-hydralazine",
							"type":"document",
							"contains":[
									
							]
						},
						{
							"title":"Ativan-lorazepam",
							"type":"document",
							"contains":[
									
							]
						},
						{
							"title":"Atropine-atropine Sulfate",
							"type":"document",
							"contains":[
									
							]
						},
						{
							"title":"Atrovent-ipratopium",
							"type":"document",
							"contains":[
									
							]
						},
						{
							"title":"Benadryl-diphenhydramine",
							"type":"document",
							"contains":[
									
							]
						},
						{
							"title":"Brethine-terbutaline Sulfate",
							"type":"document",
							"contains":[
									
							]
						},
						{
							"title":"Brillinta-tricagrelor",
							"type":"document",
							"contains":[
									
							]
						},
						{
							"title":"Calcium Chloride",
							"type":"document",
							"contains":[
									
							]
						},
						{
							"title":"Calcium Gluconate",
							"type":"document",
							"contains":[
									
							]
						},
						{
							"title":"Cardene-nicardipine",
							"type":"document",
							"contains":[
									
							]
						},
						{
							"title":"Cardizem-diltiazem",
							"type":"document",
							"contains":[
									
							]
						},
						{
							"title":"Cordarone-amiodarone",
							"type":"document",
							"contains":[
									
							]
						},
						{
							"title":"Dextrose 25, 50%",
							"type":"document",
							"contains":[
									
							]
						},
						{
							"title":"Dilantin-phenytoin",
							"type":"document",
							"contains":[
									
							]
						},
						{
							"title":"Dobutrex-dobutamine",
							"type":"document",
							"contains":[
									
							]
						},
						{
							"title":"GlucaGen-glucagon",
							"type":"document",
							"contains":[
									
							]
						},
						{
							"title":"Haldol-Haloperidol",
							"type":"document",
							"contains":[
									
							]
						},
						{
							"title":"Heparin",
							"type":"document",
							"contains":[
									
							]
						},
						{
							"title":"Humulin R-insulin",
							"type":"document",
							"contains":[
									
							]
						},
						{
							"title":"Inapsine-droperidol",
							"type":"document",
							"contains":[
									
							]
						},
						{
							"title":"Inotropin-dopamine",
							"type":"document",
							"contains":[
									
							]
						},
						{
							"title":"Ketalar-ketamine",
							"type":"document",
							"contains":[
									
							]
						},
						{
							"title":"Lasix-furosemide",
							"type":"document",
							"contains":[
									
							]
						},
						{
							"title":"Levophed-norepinephrine",
							"type":"document",
							"contains":[
									
							]
						},
						{
							"title":"Lidocaine",
							"type":"document",
							"contains":[
									
							]
						},
						{
							"title":"Lopressor-metoprolol",
							"type":"document",
							"contains":[
									
							]
						},
						{
							"title":"Magnesium Sulfate",
							"type":"document",
							"contains":[
									
							]
						},
						{
							"title":"Methergine-methylergonovine",
							"type":"document",
							"contains":[
									
							]
						},
						{
							"title":"Morphine",
							"type":"document",
							"contains":[
									
							]
						},
						{
							"title":"Narcan-naloxone",
							"type":"document",
							"contains":[
									
							]
						},
						{
							"title":"Neosynephrine-phenylephrine",
							"type":"document",
							"contains":[
									
							]
						},
						{
							"title":"Nesiritide-natrecor",
							"type":"document",
							"contains":[
									
							]
						},
						{
							"title":"Nimbex-cisatracurium",
							"type":"document",
							"contains":[
									
							]
						},
						{
							"title":"Nipride-nitroprusside",
							"type":"document",
							"contains":[
									
							]
						},
						{
							"title":"Nitroglycerin",
							"type":"document",
							"contains":[
									
							]
						},
						{
							"title":"Norcuron-vecuronium",
							"type":"document",
							"contains":[
									
							]
						},
						{
							"title":"Normodyne-labetalol",
							"type":"document",
							"contains":[
									
							]
						},
						{
							"title":"Osmitrol-mannitol",
							"type":"document",
							"contains":[
									
							]
						},
						{
							"title":"Pavulon-pancuronium Review",
							"type":"document",
							"contains":[
									
							]
						},
						{
							"title":"Phenergan-promethazine",
							"type":"document",
							"contains":[
									
							]
						},
						{
							"title":"Pitocin-oxytocin",
							"type":"document",
							"contains":[
									
							]
						},
						{
							"title":"Pitressin-vasopressin",
							"type":"document",
							"contains":[
									
							]
						},
						{
							"title":"Plavix-clopidogrel - Reviewed",
							"type":"document",
							"contains":[
									
							]
						},
						{
							"title":"Primacor-milrinone",
							"type":"document",
							"contains":[
									
							]
						},
						{
							"title":"Pronestly-procainamide",
							"type":"document",
							"contains":[
									
							]
						},
						{
							"title":"Prostin-dinoprostone",
							"type":"document",
							"contains":[
									
							]
						},
						{
							"title":"Racemic Epi-racephinephrine",
							"type":"document",
							"contains":[
									
							]
						},
						{
							"title":"Regitine-phentolamine - Reviewed",
							"type":"document",
							"contains":[
									
							]
						},
						{
							"title":"Sodium Bicarbonate - Reviewed",
							"type":"document",
							"contains":[
									
							]
						},
						{
							"title":"Solfoton-phenobarbital - Reviewed",
							"type":"document",
							"contains":[
									
							]
						},
						{
							"title":"Solu-medrol-methylprednisolone",
							"type":"document",
							"contains":[
									
							]
						},
						{
							"title":"Sublimaze-fentanyl",
							"type":"document",
							"contains":[
									
							]
						},
						{
							"title":"TPA - Reviewed",
							"type":"document",
							"contains":[
									
							]
						},
						{
							"title":"Valium-diazepam",
							"type":"document",
							"contains":[
									
							]
						},
						{
							"title":"Ventolin-albuterol",
							"type":"document",
							"contains":[
									
							]
						},
						{
							"title":"Versed-midazolam",
							"type":"document",
							"contains":[
									
							]
						},
						{
							"title":"Zemuron-rocuronium",
							"type":"document",
							"contains":[
									
							]
						},
						{
							"title":"Zofran-ondansetron - Reviewed",
							"type":"document",
							"contains":[
									
							]
						}
					]
				},
				{
					"title":"OB Impressions",
					"type":"folder",
					"contains":[
						{
							"title":"Abrupto Placenta and Placenta Previa",
							"type":"document",
							"contains":[
							
							]
						},
						{
							"title":"Cardiac Arrest in Term Pregnancy",
							"type":"document",
							"contains":[
									
							]
						},
						{
							"title":"Delivery Eminent",
							"type":"document",
							"contains":[
									
							]
						},
						{
							"title":"General High Risk OB Guidelines",
							"type":"document",
							"contains":[
									
							]
						},
						{
							"title":"Newborn Resusitation",
							"type":"document",
							"contains":[
									
							]
						},
						{
							"title":"Postpartum Hemorrhage",
							"type":"document",
							"contains":[
									
							]
						},
						{
							"title":"Pre-Term Labor",
							"type":"document",
							"contains":[
									
							]
						},
						{
							"title":"Preeclampsia and Eclampsia",
							"type":"document",
							"contains":[
									
							]
						},
						{
							"title":"Prolapsed Cord",
							"type":"document",
							"contains":[
									
							]
						}
					]
				},
				{
					"title":"Procedures",
					"type":"folder",
					"contains":[
						{
							"title":"Blood Product Administration",
							"type":"document",
							"contains":[
									
							]
						},
						{
							"title":"Cardiac Pacing - Transvenous",
							"type":"document",
							"contains":[
									
							]
						},
						{
							"title":"Continuous Positive Airway Pressure CPAP-BIPAP",
							"type":"document",
							"contains":[
									
							]
						},
						{
							"title":"Cricothyrotomy - Needle",
							"type":"document",
							"contains":[
									
							]
						},
						{
							"title":"Cricothytomy - Open",
							"type":"document",
							"contains":[
									
							]
						},
						{
							"title":"Hemorrhage - Severe",
							"type":"document",
							"contains":[
									
							]
						},
						{
							"title":"King Airway Insertion",
							"type":"document",
							"contains":[
									
							]
						},
						{
							"title":"Pericardiocentesis",
							"type":"document",
							"contains":[
									
							]
						},
						{
							"title":"Rapid Sequence Intubation",
							"type":"document",
							"contains":[
									
							]
						},
						{
							"title":"Thoracostomy",
							"type":"document",
							"contains":[
									
							]
						}
					]
				},	
				{
					"title":"Trauma Diagnoses",
					"type":"folder",
					"contains":[
						{
							"title":"Airway Management",
							"type":"document",
							"contains":[
									
							]
						},
						{
							"title":"Bites",
							"type":"document",
							"contains":[
									
							]
						},
						{
							"title":"Breathing Management",
							"type":"document",
							"contains":[
									
							]
						},
						{
							"title":"Burns-thermal, Chemical, and Electrical",
							"type":"document",
							"contains":[
									
							]
						},
						{
							"title":"Circulation Management",
							"type":"document",
							"contains":[
									
							]
						},
						{
							"title":"Closed Head Injury",
							"type":"document",
							"contains":[
									
							]
						},
						{
							"title":"Cold Injury",
							"type":"document",
							"contains":[
									
							]
						},
						{
							"title":"Decompression Syndrome, Bends",
							"type":"document",
							"contains":[
									
							]
						},
						{
							"title":"Drowning",
							"type":"document",
							"contains":[
									
							]
						},
						{
							"title":"Heat Injury",
							"type":"document",
							"contains":[
									
							]
						},
						{
							"title":"Hemorrhage Control",
							"type":"document",
							"contains":[
									
							]
						},
						{
							"title":"Medical SOP Template",
							"type":"document",
							"contains":[
									
							]
						},
						{
							"title":"OB Trauma",
							"type":"document",
							"contains":[
									
							]
						},
						{
							"title":"Orthopaedic Trauma, Major",
							"type":"document",
							"contains":[
									
							]
						},
						{
							"title":"Penetrating Trauma",
							"type":"document",
							"contains":[
									
							]
						},
						{
							"title":"Trauma, General",
							"type":"document",
							"contains":[
									
							]
						}
					]
				}
			]
		}
	]
}